{
  "users": [
    {
      "id": 1,
      "username": "testuser1",
      "firstname": "Matthew",
      "lastname": "Orson",
      "email": "testemail1@email.test",
      "locationsToVisitIds": [],
      "photo": "assets/images/pexels-elizabeth-zernetska-9292196.jpg",
      "reportedCommentIds": []
    },
    {
      "id": 2,
      "username": "testuser2",
      "firstname": "Tasha",
      "lastname": "Christopher",
      "email": "testemail2@email.test",
      "locationsToVisitIds": [
        1
      ]
    },
    {
      "id": 3,
      "username": "testuser3",
      "firstname": "Kristi",
      "lastname": "Brandee",
      "email": "testemail3@email.test",
      "locationsToVisitIds": []
    }
  ],
  "roadtrips": [
    {
      "id": 1,
      "title": "Down the East Coast",
      "description": "For our summer vacation of 2021, we decided to travel from our home state of Maine down to the sunshine state, Florida. We had a great time and met a lot of new people.",
      "datePosted": "2021-08-04 14:30",
      "ownerId": 1,
      "collaboratorIds": [
        2,
        3
      ],
      "stopIds": [
        3,
        1
      ],
      "commentIds": [
        2,
        1,
        4
      ]
    },
    {
      "id": 2,
      "title": "test roadtrip 1",
      "description": "test roadtrip desc",
      "datePosted": "2021-09-07T17:45:22.555Z",
      "ownerId": 1,
      "collaboratorIds": [],
      "stopIds": [],
      "commentIds": [
        3
      ]
    }
  ],
  "stops": [
    {
      "id": 1,
      "locationId": 1,
      "description": "Cool bride to cross with good views of the ocean."
    },
    {
      "locationId": 3,
      "description": "Good pizza place near the Atlantic",
      "id": 3
    }
  ],
  "locations": [
    {
      "id": 1,
      "title": "Bar Island Land Bridge",
      "address": null,
      "latitude": 44.394041710189725,
      "longitude": -68.21076306045076,
      "photos": [
        "assets/images/pexels-guilherme-rossi-1755680.jpg"
      ]
    },
    {
      "id": 2,
      "title": "Crescent Beach",
      "address": "24 Gold Ribbon Dr, Wells, ME 04090",
      "latitude": 43.2934818394737,
      "longitude": -70.56759799489502,
      "photos": [
        "assets/images/pexels-quang-nguyen-vinh-3355732.jpg"
      ]
    },
    {
      "title": "Charlestown Famous Pizza",
      "address": "3986 Old Post Rd, Charlestown, RI 02813",
      "latitude": 41.387318471468426,
      "longitude": -71.62471918567633,
      "id": 3,
      "photos": [
        "assets/images/pexels-sydney-troxell-708587.jpg"
      ]
    },
    {
      "id": 4,
      "title": "test",
      "address": "test",
      "latitude": 42.24145062993487,
      "longitude": -71.58766299806356,
      "photos": []
    }
  ],
  "comments": [
    {
      "id": 1,
      "text": "I stopped at a few places on this plan. Good time!",
      "datePosted": "2021-08-04T18:30:00.000Z",
      "replyIds": [],
      "parentCommentId": null,
      "ownerId": 2
    },
    {
      "text": "test1",
      "datePosted": "2021-09-07T17:05:59.933Z",
      "replyIds": [],
      "parentCommentId": null,
      "ownerId": 1,
      "id": 2
    },
    {
      "id": 3,
      "text": "asdf asd f lksdajf asd fdasjfk asdfj; asdf;l jads;jf ;asd fdsjafkhdashf lhdaslkfh alsdkjh flksd alsadl fadsf asdf asd f lksdajf asd fdasjfk asdfj; asdf;l jads;jf ;asd fdsjafkhdashf lhdaslkfh alsdkjh flksd alsadl fadsf alsdkjh flksd alsadl fadsf asdf asd f lksdajf asd fdasjfk asdfj; asdf;l jads;jf ;asd fdsjafkhdashf lhdaslkfh alsdkjh flksd alsadl fadsf alsdkjh flksd alsadl fadsf asdf asd f lksdajf asd fdasjfk asdfj; asdf;l jads;jf ;asd fdsjafkhdashf lhdaslkfh alsdkjh flksd alsadl fadsf asdf asd f lksdajf asd fdasjfk asdfj; asdf;l jads;jf ;asd fdsjafkhdashf lhdaslkfh alsdkjh flksd alsadl fadsf asdf asd f lksdajf asd fdasjfk asdfj; asdf;l jads;jf ;asd fdsjafkhdashf lhdaslkfh alsdkjh flksd alsadl fadsf alsdkjh flksd alsadl fadsf asdf asd f lksdajf asd fdasjfk asdfj; asdf;l jads;jf ;asd fdsjafkhdashf lhdaslkfh alsdkjh flksd alsadl fadsf alsdkjh flksd alsadl fadsf asdf asd f lksdajf asd fdasjfk asdfj; asdf;l jads;jf ;asd fdsjafkhdashf lhdaslkfh alsdkjh flksd alsadl fadsf",
      "datePosted": "2021-09-07T17:45:30.575Z",
      "replyIds": [
        6,
        7,
        8
      ],
      "parentCommentId": null,
      "ownerId": 1
    },
    {
      "id": 4,
      "text": "kfkjhsa dflk haslkdfh lkasjdh fkljas hdlkfjh laskjdh flkjahsdlkf hlaskdjf hlkajs dlkfj alsdkfhlkajsdhlf kjasdkfj hkasjdhfkjdshalfkjd hsalkfhkajsdhfkj ashldkf haksdjfhkasjd hfkjshaldkfhlaskdhfiwuaehfiuhsadfuh u afi hasidf hasu dhfh asldkfhlaksdfh lkasdh fl khasldfkhs adf kfkjhsa dflk haslkdfh lkasjdh fkljas hdlkfjh laskjdh flkjahsdlkf hlaskdjf hlkajs dlkfj alsdkfhlkajsdhlf kjasdkfj hkasjdhfkjdshalfkjd hsalkfhkajsdhfkj ashldkf haksdjfhkasjd hfkjshaldkfhlaskdhfiwuaehfiuhsadfuh u afi hasidf hasu dhfh asldkfhlaksdfh lkasdh fl khasldfkhs adf kfkjhsa dflk haslkdfh lkasjdh fkljas hdlkfjh laskjdh flkjahsdlkf hlaskdjf hlkajs dlkfj alsdkfhlkajsdhlf kjasdkfj hkasjdhfkjdshalfkjd hsalkfhkajsdhfkj ashldkf haksdjfhkasjd hfkjshaldkfhlaskdhfiwuaehfiuhsadfuh u afi hasidf hasu dhfh asldkfhlaksdfh lkasdh fl khasldfkhs adf kfkjhsa dflk haslkdfh lkasjdh fkljas hdlkfjh laskjdh flkjahsdlkf hlaskdjf hlkajs dlkfj alsdkfhlkajsdhlf kjasdkfj hkasjdhfkjdshalfkjd hsalkfhkajsdhfkj ashldkf haksdjfhkasjd hfkjshaldkfhlaskdhfiwuaehfiuhsadfuh u afi hasidf hasu dhfh asldkfhlaksdfh lkasdh fl khasldfkhs adf",
      "datePosted": "2021-09-28T18:29:58.786Z",
      "replyIds": [
        5
      ],
      "parentCommentId": null,
      "ownerId": 1
    },
    {
      "text": "this is a reply",
      "datePosted": "2021-09-28T18:36:51.208Z",
      "replyIds": [],
      "parentCommentId": 4,
      "ownerId": 1,
      "id": 5
    },
    {
      "text": "this is also a reply",
      "datePosted": "2021-09-28T18:37:22.456Z",
      "replyIds": [],
      "parentCommentId": 3,
      "ownerId": 1,
      "id": 6
    },
    {
      "id": 7,
      "text": "test1",
      "datePosted": "2021-09-28T18:45:56.365Z",
      "replyIds": [
        9
      ],
      "parentCommentId": 3,
      "ownerId": 1
    },
    {
      "id": 8,
      "text": "test2",
      "datePosted": "2021-09-28T18:46:01.657Z",
      "replyIds": [
        10
      ],
      "parentCommentId": 3,
      "ownerId": 1
    },
    {
      "id": 9,
      "text": "test3",
      "datePosted": "2021-09-28T18:46:05.321Z",
      "replyIds": [
        11
      ],
      "parentCommentId": 7,
      "ownerId": 1
    },
    {
      "text": "test4",
      "datePosted": "2021-09-28T18:46:09.469Z",
      "replyIds": [],
      "parentCommentId": 8,
      "ownerId": 1,
      "id": 10
    },
    {
      "text": "test5",
      "datePosted": "2021-09-28T18:46:13.481Z",
      "replyIds": [],
      "parentCommentId": 9,
      "ownerId": 1,
      "id": 11
    }
  ]
}